{
  "version": 2,
  "extractor": "papercropper",
  "figures": [
    {
      "url": "assets/figures/aaai-2026-accepted/aaai-2026-37602/fig-001.webp",
      "caption": "",
      "page": 0,
      "index": 1,
      "width": 1630,
      "height": 562,
      "label": "Figure"
    },
    {
      "url": "assets/figures/aaai-2026-accepted/aaai-2026-37602/fig-002.webp",
      "caption": "",
      "page": 0,
      "index": 2,
      "width": 1664,
      "height": 517,
      "label": "Figure"
    },
    {
      "url": "assets/figures/aaai-2026-accepted/aaai-2026-37602/fig-003.webp",
      "caption": "",
      "page": 0,
      "index": 3,
      "width": 1464,
      "height": 568,
      "label": "Figure"
    },
    {
      "url": "assets/figures/aaai-2026-accepted/aaai-2026-37602/fig-004.webp",
      "caption": "",
      "page": 0,
      "index": 4,
      "width": 867,
      "height": 734,
      "label": "Figure"
    }
  ]
}